tardis_em_analysis/__init__.py
tardis_em_analysis/_version.py
tardis_em_analysis/analysis.py
tardis_em_analysis/filament_structure.py
tardis_em_analysis/filament_utils.py
tardis_em_analysis/geometry_metrics.py
tardis_em_analysis/spatial_graph_utils.py
tardis_em_analysis/utils.py
tardis_em_analysis/mt_classification/__init__.py
tardis_em_analysis/mt_classification/mt_classes.py
tardis_em_analysis/mt_classification/utils.py
tardis_em_analysis/stitch_volume/__init__.py
tardis_em_analysis/stitch_volume/align_tomograms.py
tardis_em_analysis/stitch_volume/utils.py
tardis_em_analysis-0.3.22.dist-info/licenses/LICENSE
tardis_em_analysis-0.3.22.dist-info/METADATA
tardis_em_analysis-0.3.22.dist-info/WHEEL
tardis_em_analysis-0.3.22.dist-info/top_level.txt
tardis_em_analysis-0.3.22.dist-info/RECORD
