Metadata-Version: 2.4
Name: tardis_em_analysis
Version: 0.3.22
Summary: Collection of analysis libraries used by TARDIS-EM and napari-tardis-em.
Home-page: https://github.com/SMLC-NYSBC/tardis_em_analysis
Author: Robert Kiewisz, Tristan Bepler
Author-email: robert.kiewisz@gmail.com, rkiewisz@nysbc.org, tbepler@nysbc.org
License: MIT
Keywords: tardis-em,analysis,filaments,membranes
Classifier: Development Status :: 5 - Production/Stable
Classifier: Intended Audience :: Education
Classifier: Environment :: Console
Classifier: Environment :: GPU :: NVIDIA CUDA :: 11
Classifier: Natural Language :: English
Classifier: Programming Language :: Python :: 3.10
Classifier: Programming Language :: Python :: 3.11
Requires-Python: !=3.12,>=3.10
License-File: LICENSE
Requires-Dist: torch>2.0.0
Requires-Dist: numpy>=2.0.0
Requires-Dist: pandas>=2.2.0
Requires-Dist: tifffile
Requires-Dist: imagecodecs
Requires-Dist: scikit-learn>1.0.1
Requires-Dist: scikit-image>0.19.2
Requires-Dist: scipy>=1.10.0
Requires-Dist: opencv-python>=4.12.0.0
Requires-Dist: ipython>8.10.0
Requires-Dist: setuptools>=67.6.0
Dynamic: license-file
